damn_simple_jsonrpc_server-0.5.0.dist-info/licenses/LICENSE.md
jsonrpcserver/__init__.py
jsonrpcserver/introspection.py
tests/test_server.py
damn_simple_jsonrpc_server-0.5.0.dist-info/METADATA
damn_simple_jsonrpc_server-0.5.0.dist-info/WHEEL
damn_simple_jsonrpc_server-0.5.0.dist-info/top_level.txt
damn_simple_jsonrpc_server-0.5.0.dist-info/RECORD
