Metadata-Version: 2.4
Name: damn-simple-jsonrpc-server
Version: 0.5.0
Summary: Damn simple, framework-agnostic JSON-RPC server
Author-email: Marcin Nowak <marcin.j.nowak@gmail.com>
License: BSD License
Project-URL: Homepage, https://github.com/marcinn/json-rpc-server
Keywords: web,json,rpc,python,server
Classifier: Development Status :: 3 - Alpha
Classifier: Environment :: Web Environment
Classifier: License :: OSI Approved :: BSD License
Classifier: Programming Language :: Python :: 3.7
Classifier: Programming Language :: Python :: 3.8
Classifier: Programming Language :: Python :: 3.9
Classifier: Programming Language :: Python :: 3.10
Classifier: Programming Language :: Python :: 3.11
Classifier: Programming Language :: Python :: 3.12
Classifier: Programming Language :: Python :: 3.13
Classifier: Topic :: Internet :: WWW/HTTP
Classifier: Topic :: Software Development :: Libraries :: Python Modules
Requires-Python: >=3.7
License-File: LICENSE.md
Provides-Extra: dev
Requires-Dist: build; extra == "dev"
Requires-Dist: twine; extra == "dev"
Dynamic: license-file
